snipe/__init__.py
snipe/_rooster.py
snipe/context.py
snipe/editor.py
snipe/filters.py
snipe/gap.py
snipe/help.py
snipe/interactive.py
snipe/irccloud.py
snipe/keymap.py
snipe/main.py
snipe/messager.py
snipe/messages.py
snipe/prompt.py
snipe/repl.py
snipe/roost.py
snipe/slack.py
snipe/text.py
snipe/ttycolor.py
snipe/ttyfe.py
snipe/util.py
snipe/window.py
snipe/zcode.py
snipe/zulip.py
snipe/_roost_python/__init__.py
snipe/_roost_python/gss.py
snipe/_roost_python/gss_ctypes.py
snipe/_roost_python/krb5.py
snipe/_roost_python/krb5_ctypes.py
snipe_im-0.dev2.dist-info/DESCRIPTION.rst
snipe_im-0.dev2.dist-info/METADATA
snipe_im-0.dev2.dist-info/RECORD
snipe_im-0.dev2.dist-info/WHEEL
snipe_im-0.dev2.dist-info/entry_points.txt
snipe_im-0.dev2.dist-info/metadata.json
snipe_im-0.dev2.dist-info/top_level.txt
